{
  "name": "GitHub Dark Dimmed",
  "slug": "github-dark-dimmed",
  "isDark": true,
  "tags": [
    "dark",
    "wcag-aaa",
    "wcag-aa",
    "ansi-legible",
    "popular"
  ],
  "source": "iterm2-color-schemes",
  "sourceUrl": "https://github.com/mbadolato/iTerm2-Color-Schemes/blob/a2c7b60293a81d82767893d89bc7599342c04cbf/windowsterminal/GitHub Dark Dimmed.json",
  "upstreamSha": "a2c7b60293a81d82767893d89bc7599342c04cbf",
  "updatedAt": "2026-04-21T02:02:19.058Z",
  "colors": {
    "background": {
      "hex": "#22272e",
      "oklch": {
        "l": 0.2708,
        "c": 0.0149,
        "h": 256.8
      },
      "oklchCss": "oklch(0.271 0.015 256.8)"
    },
    "foreground": {
      "hex": "#adbac7",
      "oklch": {
        "l": 0.7829,
        "c": 0.0235,
        "h": 248.1
      },
      "oklchCss": "oklch(0.783 0.024 248.1)"
    },
    "cursor": {
      "hex": "#539bf5",
      "oklch": {
        "l": 0.6841,
        "c": 0.152,
        "h": 255.1
      },
      "oklchCss": "oklch(0.684 0.152 255.1)"
    },
    "selection": {
      "hex": "#adbac7",
      "oklch": {
        "l": 0.7829,
        "c": 0.0235,
        "h": 248.1
      },
      "oklchCss": "oklch(0.783 0.024 248.1)"
    },
    "black": {
      "hex": "#545d68",
      "oklch": {
        "l": 0.4745,
        "c": 0.0211,
        "h": 253.5
      },
      "oklchCss": "oklch(0.475 0.021 253.5)"
    },
    "red": {
      "hex": "#f47067",
      "oklch": {
        "l": 0.7017,
        "c": 0.1642,
        "h": 26.1
      },
      "oklchCss": "oklch(0.702 0.164 26.1)"
    },
    "green": {
      "hex": "#57ab5a",
      "oklch": {
        "l": 0.6687,
        "c": 0.1421,
        "h": 144.5
      },
      "oklchCss": "oklch(0.669 0.142 144.5)"
    },
    "yellow": {
      "hex": "#c69026",
      "oklch": {
        "l": 0.6888,
        "c": 0.1313,
        "h": 79.1
      },
      "oklchCss": "oklch(0.689 0.131 79.1)"
    },
    "blue": {
      "hex": "#539bf5",
      "oklch": {
        "l": 0.6841,
        "c": 0.152,
        "h": 255.1
      },
      "oklchCss": "oklch(0.684 0.152 255.1)"
    },
    "purple": {
      "hex": "#b083f0",
      "oklch": {
        "l": 0.6981,
        "c": 0.1599,
        "h": 301.4
      },
      "oklchCss": "oklch(0.698 0.16 301.4)"
    },
    "cyan": {
      "hex": "#39c5cf",
      "oklch": {
        "l": 0.7555,
        "c": 0.1155,
        "h": 202.1
      },
      "oklchCss": "oklch(0.756 0.116 202.1)"
    },
    "white": {
      "hex": "#909dab",
      "oklch": {
        "l": 0.6902,
        "c": 0.0254,
        "h": 250.2
      },
      "oklchCss": "oklch(0.69 0.025 250.2)"
    },
    "brightBlack": {
      "hex": "#636e7b",
      "oklch": {
        "l": 0.5336,
        "c": 0.0244,
        "h": 252.6
      },
      "oklchCss": "oklch(0.534 0.024 252.6)"
    },
    "brightRed": {
      "hex": "#ff938a",
      "oklch": {
        "l": 0.7755,
        "c": 0.1316,
        "h": 25.6
      },
      "oklchCss": "oklch(0.776 0.132 25.6)"
    },
    "brightGreen": {
      "hex": "#6bc46d",
      "oklch": {
        "l": 0.7436,
        "c": 0.1491,
        "h": 144.3
      },
      "oklchCss": "oklch(0.744 0.149 144.3)"
    },
    "brightYellow": {
      "hex": "#daaa3f",
      "oklch": {
        "l": 0.7633,
        "c": 0.1331,
        "h": 83.9
      },
      "oklchCss": "oklch(0.763 0.133 83.9)"
    },
    "brightBlue": {
      "hex": "#6cb6ff",
      "oklch": {
        "l": 0.7581,
        "c": 0.1292,
        "h": 249.6
      },
      "oklchCss": "oklch(0.758 0.129 249.6)"
    },
    "brightPurple": {
      "hex": "#dcbdfb",
      "oklch": {
        "l": 0.8454,
        "c": 0.0908,
        "h": 307.3
      },
      "oklchCss": "oklch(0.845 0.091 307.3)"
    },
    "brightCyan": {
      "hex": "#56d4dd",
      "oklch": {
        "l": 0.8036,
        "c": 0.1107,
        "h": 201.8
      },
      "oklchCss": "oklch(0.804 0.111 201.8)"
    },
    "brightWhite": {
      "hex": "#cdd9e5",
      "oklch": {
        "l": 0.8798,
        "c": 0.0211,
        "h": 248.1
      },
      "oklchCss": "oklch(0.88 0.021 248.1)"
    }
  },
  "contrast": {
    "fgOnBg": 7.601990586445604,
    "minAnsi": 5.2593014228844295,
    "minAnsiSlot": "purple"
  }
}
