{
  "name": "Keys Ocean Sunset",
  "slug": "keys-ocean-sunset",
  "isDark": true,
  "tags": [
    "dark",
    "high-contrast",
    "wcag-aaa",
    "wcag-aa",
    "ansi-legible"
  ],
  "source": "iterm2-color-schemes",
  "sourceUrl": "https://github.com/mbadolato/iTerm2-Color-Schemes/blob/97e244cf98a0eb2ce4339d2069ec1bba6c81f141/windowsterminal/Keys Ocean Sunset.json",
  "upstreamSha": "97e244cf98a0eb2ce4339d2069ec1bba6c81f141",
  "updatedAt": "2026-07-23T16:20:55.215Z",
  "colors": {
    "background": {
      "hex": "#0a1018",
      "oklch": {
        "l": 0.171,
        "c": 0.0193,
        "h": 255.8
      },
      "oklchCss": "oklch(0.171 0.019 255.8)"
    },
    "foreground": {
      "hex": "#b8c8dc",
      "oklch": {
        "l": 0.8269,
        "c": 0.0331,
        "h": 254
      },
      "oklchCss": "oklch(0.827 0.033 254)"
    },
    "cursor": {
      "hex": "#fc9077",
      "oklch": {
        "l": 0.7632,
        "c": 0.1362,
        "h": 34
      },
      "oklchCss": "oklch(0.763 0.136 34)"
    },
    "selection": {
      "hex": "#1a2430",
      "oklch": {
        "l": 0.2565,
        "c": 0.0269,
        "h": 253.3
      },
      "oklchCss": "oklch(0.257 0.027 253.3)"
    },
    "black": {
      "hex": "#101927",
      "oklch": {
        "l": 0.2121,
        "c": 0.0309,
        "h": 259
      },
      "oklchCss": "oklch(0.212 0.031 259)"
    },
    "red": {
      "hex": "#e85a52",
      "oklch": {
        "l": 0.6515,
        "c": 0.1779,
        "h": 26.4
      },
      "oklchCss": "oklch(0.652 0.178 26.4)"
    },
    "green": {
      "hex": "#4a9a72",
      "oklch": {
        "l": 0.6244,
        "c": 0.1004,
        "h": 159.7
      },
      "oklchCss": "oklch(0.624 0.1 159.7)"
    },
    "yellow": {
      "hex": "#e89a2e",
      "oklch": {
        "l": 0.7473,
        "c": 0.1476,
        "h": 69.6
      },
      "oklchCss": "oklch(0.747 0.148 69.6)"
    },
    "blue": {
      "hex": "#5288b8",
      "oklch": {
        "l": 0.6094,
        "c": 0.0933,
        "h": 246.8
      },
      "oklchCss": "oklch(0.609 0.093 246.8)"
    },
    "purple": {
      "hex": "#bc5090",
      "oklch": {
        "l": 0.5897,
        "c": 0.1565,
        "h": 346.4
      },
      "oklchCss": "oklch(0.59 0.157 346.4)"
    },
    "cyan": {
      "hex": "#5ec8c8",
      "oklch": {
        "l": 0.7708,
        "c": 0.0977,
        "h": 195.3
      },
      "oklchCss": "oklch(0.771 0.098 195.3)"
    },
    "white": {
      "hex": "#a5b5d5",
      "oklch": {
        "l": 0.7715,
        "c": 0.0492,
        "h": 264.2
      },
      "oklchCss": "oklch(0.772 0.049 264.2)"
    },
    "brightBlack": {
      "hex": "#344658",
      "oklch": {
        "l": 0.3865,
        "c": 0.0384,
        "h": 248.9
      },
      "oklchCss": "oklch(0.387 0.038 248.9)"
    },
    "brightRed": {
      "hex": "#fc9077",
      "oklch": {
        "l": 0.7632,
        "c": 0.1362,
        "h": 34
      },
      "oklchCss": "oklch(0.763 0.136 34)"
    },
    "brightGreen": {
      "hex": "#62c48e",
      "oklch": {
        "l": 0.7463,
        "c": 0.1224,
        "h": 157.4
      },
      "oklchCss": "oklch(0.746 0.122 157.4)"
    },
    "brightYellow": {
      "hex": "#ffcb9a",
      "oklch": {
        "l": 0.8766,
        "c": 0.0868,
        "h": 64.6
      },
      "oklchCss": "oklch(0.877 0.087 64.6)"
    },
    "brightBlue": {
      "hex": "#5a8fd4",
      "oklch": {
        "l": 0.6432,
        "c": 0.1187,
        "h": 255.6
      },
      "oklchCss": "oklch(0.643 0.119 255.6)"
    },
    "brightPurple": {
      "hex": "#fdbfde",
      "oklch": {
        "l": 0.8695,
        "c": 0.081,
        "h": 347.4
      },
      "oklchCss": "oklch(0.87 0.081 347.4)"
    },
    "brightCyan": {
      "hex": "#7ed4e0",
      "oklch": {
        "l": 0.8199,
        "c": 0.0848,
        "h": 207.1
      },
      "oklchCss": "oklch(0.82 0.085 207.1)"
    },
    "brightWhite": {
      "hex": "#fff5be",
      "oklch": {
        "l": 0.9648,
        "c": 0.0711,
        "h": 98.9
      },
      "oklchCss": "oklch(0.965 0.071 98.9)"
    }
  },
  "contrast": {
    "fgOnBg": 11.209877612459675,
    "minAnsi": 4.261415984732175,
    "minAnsiSlot": "purple"
  },
  "accent": {
    "source": "cursor",
    "hex": "#fc9077",
    "oklch": {
      "l": 0.7632,
      "c": 0.1362,
      "h": 34
    },
    "oklchCss": "oklch(0.763 0.136 34)"
  }
}
