{
  "name": "Monokai Pro Light Sun",
  "slug": "monokai-pro-light-sun",
  "isDark": false,
  "tags": [
    "light",
    "high-contrast",
    "wcag-aaa",
    "wcag-aa",
    "cursor-visible",
    "selection-legible",
    "popular"
  ],
  "source": "iterm2-color-schemes",
  "sourceUrl": "https://github.com/mbadolato/iTerm2-Color-Schemes/blob/97e244cf98a0eb2ce4339d2069ec1bba6c81f141/windowsterminal/Monokai Pro Light Sun.json",
  "upstreamSha": "97e244cf98a0eb2ce4339d2069ec1bba6c81f141",
  "updatedAt": "2026-07-23T18:15:18.776Z",
  "colors": {
    "background": {
      "hex": "#f8efe7",
      "oklch": {
        "l": 0.957,
        "c": 0.0145,
        "h": 64.3
      },
      "oklchCss": "oklch(0.957 0.015 64.3)"
    },
    "foreground": {
      "hex": "#2c232e",
      "oklch": {
        "l": 0.2711,
        "c": 0.0238,
        "h": 320.1
      },
      "oklchCss": "oklch(0.271 0.024 320.1)"
    },
    "cursor": {
      "hex": "#72696d",
      "oklch": {
        "l": 0.5304,
        "c": 0.0128,
        "h": 348.8
      },
      "oklchCss": "oklch(0.53 0.013 348.8)"
    },
    "selection": {
      "hex": "#beb5b3",
      "oklch": {
        "l": 0.7799,
        "c": 0.0107,
        "h": 32.5
      },
      "oklchCss": "oklch(0.78 0.011 32.5)"
    },
    "black": {
      "hex": "#f8efe7",
      "oklch": {
        "l": 0.957,
        "c": 0.0145,
        "h": 64.3
      },
      "oklchCss": "oklch(0.957 0.015 64.3)"
    },
    "red": {
      "hex": "#ce4770",
      "oklch": {
        "l": 0.5952,
        "c": 0.1727,
        "h": 5.4
      },
      "oklchCss": "oklch(0.595 0.173 5.4)"
    },
    "green": {
      "hex": "#218871",
      "oklch": {
        "l": 0.5638,
        "c": 0.0978,
        "h": 173.9
      },
      "oklchCss": "oklch(0.564 0.098 173.9)"
    },
    "yellow": {
      "hex": "#b16803",
      "oklch": {
        "l": 0.586,
        "c": 0.1318,
        "h": 63.9
      },
      "oklchCss": "oklch(0.586 0.132 63.9)"
    },
    "blue": {
      "hex": "#d4572b",
      "oklch": {
        "l": 0.6121,
        "c": 0.1679,
        "h": 38.8
      },
      "oklchCss": "oklch(0.612 0.168 38.8)"
    },
    "purple": {
      "hex": "#6851a2",
      "oklch": {
        "l": 0.497,
        "c": 0.1262,
        "h": 294.4
      },
      "oklchCss": "oklch(0.497 0.126 294.4)"
    },
    "cyan": {
      "hex": "#2473b6",
      "oklch": {
        "l": 0.5421,
        "c": 0.1286,
        "h": 248.7
      },
      "oklchCss": "oklch(0.542 0.129 248.7)"
    },
    "white": {
      "hex": "#2c232e",
      "oklch": {
        "l": 0.2711,
        "c": 0.0238,
        "h": 320.1
      },
      "oklchCss": "oklch(0.271 0.024 320.1)"
    },
    "brightBlack": {
      "hex": "#a59c9c",
      "oklch": {
        "l": 0.7004,
        "c": 0.0105,
        "h": 17.4
      },
      "oklchCss": "oklch(0.7 0.011 17.4)"
    },
    "brightRed": {
      "hex": "#ce4770",
      "oklch": {
        "l": 0.5952,
        "c": 0.1727,
        "h": 5.4
      },
      "oklchCss": "oklch(0.595 0.173 5.4)"
    },
    "brightGreen": {
      "hex": "#218871",
      "oklch": {
        "l": 0.5638,
        "c": 0.0978,
        "h": 173.9
      },
      "oklchCss": "oklch(0.564 0.098 173.9)"
    },
    "brightYellow": {
      "hex": "#b16803",
      "oklch": {
        "l": 0.586,
        "c": 0.1318,
        "h": 63.9
      },
      "oklchCss": "oklch(0.586 0.132 63.9)"
    },
    "brightBlue": {
      "hex": "#d4572b",
      "oklch": {
        "l": 0.6121,
        "c": 0.1679,
        "h": 38.8
      },
      "oklchCss": "oklch(0.612 0.168 38.8)"
    },
    "brightPurple": {
      "hex": "#6851a2",
      "oklch": {
        "l": 0.497,
        "c": 0.1262,
        "h": 294.4
      },
      "oklchCss": "oklch(0.497 0.126 294.4)"
    },
    "brightCyan": {
      "hex": "#2473b6",
      "oklch": {
        "l": 0.5421,
        "c": 0.1286,
        "h": 248.7
      },
      "oklchCss": "oklch(0.542 0.129 248.7)"
    },
    "brightWhite": {
      "hex": "#2c232e",
      "oklch": {
        "l": 0.2711,
        "c": 0.0238,
        "h": 320.1
      },
      "oklchCss": "oklch(0.271 0.024 320.1)"
    }
  },
  "contrast": {
    "fgOnBg": 13.332623545205923,
    "minAnsi": 1,
    "minAnsiSlot": "black",
    "cursorOnBg": 4.673260401820863,
    "selectionContrast": 7.5344094668772925,
    "brightnessOrdered": false,
    "brightnessViolations": [
      "brightBlack",
      "brightRed",
      "brightGreen",
      "brightYellow",
      "brightBlue",
      "brightPurple",
      "brightCyan",
      "brightWhite"
    ]
  },
  "accent": {
    "source": "red",
    "hex": "#ce4770",
    "oklch": {
      "l": 0.5952,
      "c": 0.1727,
      "h": 5.4
    },
    "oklchCss": "oklch(0.595 0.173 5.4)"
  },
  "dataviz": {
    "categorical": [
      {
        "hex": "#ce4770",
        "oklch": {
          "l": 0.5952,
          "c": 0.1727,
          "h": 5.4
        },
        "oklchCss": "oklch(0.595 0.173 5.4)"
      },
      {
        "hex": "#218871",
        "oklch": {
          "l": 0.5638,
          "c": 0.0978,
          "h": 173.9
        },
        "oklchCss": "oklch(0.564 0.098 173.9)"
      },
      {
        "hex": "#2473b6",
        "oklch": {
          "l": 0.5421,
          "c": 0.1286,
          "h": 248.7
        },
        "oklchCss": "oklch(0.542 0.129 248.7)"
      },
      {
        "hex": "#b16803",
        "oklch": {
          "l": 0.586,
          "c": 0.1318,
          "h": 63.9
        },
        "oklchCss": "oklch(0.586 0.132 63.9)"
      },
      {
        "hex": "#6851a2",
        "oklch": {
          "l": 0.497,
          "c": 0.1262,
          "h": 294.4
        },
        "oklchCss": "oklch(0.497 0.126 294.4)"
      },
      {
        "hex": "#d4572b",
        "oklch": {
          "l": 0.6121,
          "c": 0.1679,
          "h": 38.8
        },
        "oklchCss": "oklch(0.612 0.168 38.8)"
      }
    ],
    "sequential": [
      {
        "hex": "#f1f1f1",
        "oklch": {
          "l": 0.957,
          "c": 0,
          "h": 5.4
        },
        "oklchCss": "oklch(0.957 0 5.4)"
      },
      {
        "hex": "#efd5da",
        "oklch": {
          "l": 0.8967,
          "c": 0.0288,
          "h": 5.4
        },
        "oklchCss": "oklch(0.897 0.029 5.4)"
      },
      {
        "hex": "#ebbac4",
        "oklch": {
          "l": 0.8364,
          "c": 0.0576,
          "h": 5.4
        },
        "oklchCss": "oklch(0.836 0.058 5.4)"
      },
      {
        "hex": "#e69fae",
        "oklch": {
          "l": 0.7761,
          "c": 0.0864,
          "h": 5.4
        },
        "oklchCss": "oklch(0.776 0.086 5.4)"
      },
      {
        "hex": "#e08499",
        "oklch": {
          "l": 0.7158,
          "c": 0.1151,
          "h": 5.4
        },
        "oklchCss": "oklch(0.716 0.115 5.4)"
      },
      {
        "hex": "#d76784",
        "oklch": {
          "l": 0.6555,
          "c": 0.1439,
          "h": 5.4
        },
        "oklchCss": "oklch(0.656 0.144 5.4)"
      },
      {
        "hex": "#ce4770",
        "oklch": {
          "l": 0.5952,
          "c": 0.1727,
          "h": 5.4
        },
        "oklchCss": "oklch(0.595 0.173 5.4)"
      }
    ],
    "diverging": [
      {
        "hex": "#ce4770",
        "oklch": {
          "l": 0.5952,
          "c": 0.1727,
          "h": 5.4
        },
        "oklchCss": "oklch(0.595 0.173 5.4)"
      },
      {
        "hex": "#b65d73",
        "oklch": {
          "l": 0.59,
          "c": 0.1176,
          "h": 5.4
        },
        "oklchCss": "oklch(0.59 0.118 5.4)"
      },
      {
        "hex": "#9c6c76",
        "oklch": {
          "l": 0.5847,
          "c": 0.0626,
          "h": 5.4
        },
        "oklchCss": "oklch(0.585 0.063 5.4)"
      },
      {
        "hex": "#7e7879",
        "oklch": {
          "l": 0.5795,
          "c": 0.0075,
          "h": 5.4
        },
        "oklchCss": "oklch(0.58 0.008 5.4)"
      },
      {
        "hex": "#628077",
        "oklch": {
          "l": 0.5743,
          "c": 0.0376,
          "h": 173.9
        },
        "oklchCss": "oklch(0.574 0.038 173.9)"
      },
      {
        "hex": "#498474",
        "oklch": {
          "l": 0.569,
          "c": 0.0677,
          "h": 173.9
        },
        "oklchCss": "oklch(0.569 0.068 173.9)"
      },
      {
        "hex": "#218871",
        "oklch": {
          "l": 0.5638,
          "c": 0.0978,
          "h": 173.9
        },
        "oklchCss": "oklch(0.564 0.098 173.9)"
      }
    ]
  }
}
