{
  "name": "Obsidian",
  "slug": "obsidian",
  "isDark": true,
  "tags": [
    "dark",
    "wcag-aaa",
    "wcag-aa"
  ],
  "source": "iterm2-color-schemes",
  "sourceUrl": "https://github.com/mbadolato/iTerm2-Color-Schemes/blob/a2c7b60293a81d82767893d89bc7599342c04cbf/windowsterminal/Obsidian.json",
  "upstreamSha": "a2c7b60293a81d82767893d89bc7599342c04cbf",
  "updatedAt": "2026-04-21T02:02:19.058Z",
  "colors": {
    "background": {
      "hex": "#283033",
      "oklch": {
        "l": 0.3028,
        "c": 0.0123,
        "h": 222.4
      },
      "oklchCss": "oklch(0.303 0.012 222.4)"
    },
    "foreground": {
      "hex": "#cdcdcd",
      "oklch": {
        "l": 0.8483,
        "c": 0,
        "h": 0
      },
      "oklchCss": "oklch(0.848 0 0)"
    },
    "cursor": {
      "hex": "#c0cad0",
      "oklch": {
        "l": 0.8331,
        "c": 0.0138,
        "h": 233.8
      },
      "oklchCss": "oklch(0.833 0.014 233.8)"
    },
    "selection": {
      "hex": "#3e4c4f",
      "oklch": {
        "l": 0.4055,
        "c": 0.0185,
        "h": 212.1
      },
      "oklchCss": "oklch(0.406 0.019 212.1)"
    },
    "black": {
      "hex": "#000000",
      "oklch": {
        "l": 0,
        "c": 0,
        "h": 0
      },
      "oklchCss": "oklch(0 0 0)"
    },
    "red": {
      "hex": "#b30d0e",
      "oklch": {
        "l": 0.486,
        "c": 0.193,
        "h": 28.4
      },
      "oklchCss": "oklch(0.486 0.193 28.4)"
    },
    "green": {
      "hex": "#00bb00",
      "oklch": {
        "l": 0.6863,
        "c": 0.2335,
        "h": 142.5
      },
      "oklchCss": "oklch(0.686 0.234 142.5)"
    },
    "yellow": {
      "hex": "#fecd22",
      "oklch": {
        "l": 0.8668,
        "c": 0.1711,
        "h": 90.5
      },
      "oklchCss": "oklch(0.867 0.171 90.5)"
    },
    "blue": {
      "hex": "#3a9bdb",
      "oklch": {
        "l": 0.6616,
        "c": 0.1304,
        "h": 241.8
      },
      "oklchCss": "oklch(0.662 0.13 241.8)"
    },
    "purple": {
      "hex": "#bb00bb",
      "oklch": {
        "l": 0.5558,
        "c": 0.2554,
        "h": 328.4
      },
      "oklchCss": "oklch(0.556 0.255 328.4)"
    },
    "cyan": {
      "hex": "#00bbbb",
      "oklch": {
        "l": 0.7171,
        "c": 0.1224,
        "h": 194.8
      },
      "oklchCss": "oklch(0.717 0.122 194.8)"
    },
    "white": {
      "hex": "#bbbbbb",
      "oklch": {
        "l": 0.7921,
        "c": 0,
        "h": 0
      },
      "oklchCss": "oklch(0.792 0 0)"
    },
    "brightBlack": {
      "hex": "#555555",
      "oklch": {
        "l": 0.4495,
        "c": 0,
        "h": 0
      },
      "oklchCss": "oklch(0.45 0 0)"
    },
    "brightRed": {
      "hex": "#ff0003",
      "oklch": {
        "l": 0.628,
        "c": 0.2576,
        "h": 29.1
      },
      "oklchCss": "oklch(0.628 0.258 29.1)"
    },
    "brightGreen": {
      "hex": "#93c863",
      "oklch": {
        "l": 0.7733,
        "c": 0.1432,
        "h": 131.8
      },
      "oklchCss": "oklch(0.773 0.143 131.8)"
    },
    "brightYellow": {
      "hex": "#fef874",
      "oklch": {
        "l": 0.9586,
        "c": 0.153,
        "h": 106.6
      },
      "oklchCss": "oklch(0.959 0.153 106.6)"
    },
    "brightBlue": {
      "hex": "#a1d7ff",
      "oklch": {
        "l": 0.8558,
        "c": 0.079,
        "h": 240.9
      },
      "oklchCss": "oklch(0.856 0.079 240.9)"
    },
    "brightPurple": {
      "hex": "#ff55ff",
      "oklch": {
        "l": 0.7401,
        "c": 0.2718,
        "h": 327.9
      },
      "oklchCss": "oklch(0.74 0.272 327.9)"
    },
    "brightCyan": {
      "hex": "#55ffff",
      "oklch": {
        "l": 0.915,
        "c": 0.1365,
        "h": 195
      },
      "oklchCss": "oklch(0.915 0.137 195)"
    },
    "brightWhite": {
      "hex": "#ffffff",
      "oklch": {
        "l": 1,
        "c": 0,
        "h": 0
      },
      "oklchCss": "oklch(1 0 0)"
    }
  },
  "contrast": {
    "fgOnBg": 8.463511117836331,
    "minAnsi": 1.9096858460763608,
    "minAnsiSlot": "red"
  }
}
