{
  "name": "Snazzy Soft",
  "slug": "snazzy-soft",
  "isDark": true,
  "tags": [
    "dark",
    "high-contrast"
  ],
  "source": "iterm2-color-schemes",
  "sourceUrl": "https://github.com/mbadolato/iTerm2-Color-Schemes/blob/a2c7b60293a81d82767893d89bc7599342c04cbf/windowsterminal/Snazzy Soft.json",
  "upstreamSha": "a2c7b60293a81d82767893d89bc7599342c04cbf",
  "updatedAt": "2026-04-14T05:13:46.450Z",
  "colors": {
    "background": {
      "hex": "#282a36",
      "oklch": {
        "l": 0.2882,
        "c": 0.0221,
        "h": 277.5
      },
      "oklchCss": "oklch(0.288 0.022 277.5)"
    },
    "foreground": {
      "hex": "#eff0eb",
      "oklch": {
        "l": 0.953,
        "c": 0.0067,
        "h": 115.7
      },
      "oklchCss": "oklch(0.953 0.007 115.7)"
    },
    "cursor": {
      "hex": "#eaeaea",
      "oklch": {
        "l": 0.937,
        "c": 0,
        "h": 0
      },
      "oklchCss": "oklch(0.937 0 0)"
    },
    "selection": {
      "hex": "#92bcd0",
      "oklch": {
        "l": 0.7718,
        "c": 0.0531,
        "h": 228.7
      },
      "oklchCss": "oklch(0.772 0.053 228.7)"
    },
    "black": {
      "hex": "#000000",
      "oklch": {
        "l": 0,
        "c": 0,
        "h": 0
      },
      "oklchCss": "oklch(0 0 0)"
    },
    "red": {
      "hex": "#ff5c57",
      "oklch": {
        "l": 0.6902,
        "c": 0.1993,
        "h": 25.5
      },
      "oklchCss": "oklch(0.69 0.199 25.5)"
    },
    "green": {
      "hex": "#5af78e",
      "oklch": {
        "l": 0.869,
        "c": 0.1958,
        "h": 150.9
      },
      "oklchCss": "oklch(0.869 0.196 150.9)"
    },
    "yellow": {
      "hex": "#f3f99d",
      "oklch": {
        "l": 0.9574,
        "c": 0.1146,
        "h": 111.6
      },
      "oklchCss": "oklch(0.957 0.115 111.6)"
    },
    "blue": {
      "hex": "#57c7ff",
      "oklch": {
        "l": 0.7876,
        "c": 0.1286,
        "h": 233.6
      },
      "oklchCss": "oklch(0.788 0.129 233.6)"
    },
    "purple": {
      "hex": "#ff6ac1",
      "oklch": {
        "l": 0.7341,
        "c": 0.2024,
        "h": 347.1
      },
      "oklchCss": "oklch(0.734 0.202 347.1)"
    },
    "cyan": {
      "hex": "#9aedfe",
      "oklch": {
        "l": 0.8988,
        "c": 0.0838,
        "h": 212
      },
      "oklchCss": "oklch(0.899 0.084 212)"
    },
    "white": {
      "hex": "#f1f1f0",
      "oklch": {
        "l": 0.9579,
        "c": 0.0013,
        "h": 106.4
      },
      "oklchCss": "oklch(0.958 0.001 106.4)"
    },
    "brightBlack": {
      "hex": "#686868",
      "oklch": {
        "l": 0.5173,
        "c": 0,
        "h": 0
      },
      "oklchCss": "oklch(0.517 0 0)"
    },
    "brightRed": {
      "hex": "#ff5c57",
      "oklch": {
        "l": 0.6902,
        "c": 0.1993,
        "h": 25.5
      },
      "oklchCss": "oklch(0.69 0.199 25.5)"
    },
    "brightGreen": {
      "hex": "#5af78e",
      "oklch": {
        "l": 0.869,
        "c": 0.1958,
        "h": 150.9
      },
      "oklchCss": "oklch(0.869 0.196 150.9)"
    },
    "brightYellow": {
      "hex": "#f3f99d",
      "oklch": {
        "l": 0.9574,
        "c": 0.1146,
        "h": 111.6
      },
      "oklchCss": "oklch(0.957 0.115 111.6)"
    },
    "brightBlue": {
      "hex": "#57c7ff",
      "oklch": {
        "l": 0.7876,
        "c": 0.1286,
        "h": 233.6
      },
      "oklchCss": "oklch(0.788 0.129 233.6)"
    },
    "brightPurple": {
      "hex": "#ff6ac1",
      "oklch": {
        "l": 0.7341,
        "c": 0.2024,
        "h": 347.1
      },
      "oklchCss": "oklch(0.734 0.202 347.1)"
    },
    "brightCyan": {
      "hex": "#9aedfe",
      "oklch": {
        "l": 0.8988,
        "c": 0.0838,
        "h": 212
      },
      "oklchCss": "oklch(0.899 0.084 212)"
    },
    "brightWhite": {
      "hex": "#f1f1f0",
      "oklch": {
        "l": 0.9579,
        "c": 0.0013,
        "h": 106.4
      },
      "oklchCss": "oklch(0.958 0.001 106.4)"
    }
  }
}
