{
  "name": "Velvet Court",
  "slug": "velvet-court",
  "isDark": true,
  "tags": [
    "dark",
    "high-contrast",
    "wcag-aaa",
    "wcag-aa",
    "ansi-legible",
    "cursor-visible",
    "selection-legible",
    "cvd-caution"
  ],
  "source": "iterm2-color-schemes",
  "sourceUrl": "https://github.com/mbadolato/iTerm2-Color-Schemes/blob/97e244cf98a0eb2ce4339d2069ec1bba6c81f141/windowsterminal/Velvet Court.json",
  "upstreamSha": "97e244cf98a0eb2ce4339d2069ec1bba6c81f141",
  "updatedAt": "2026-07-23T18:56:28.176Z",
  "colors": {
    "background": {
      "hex": "#1f0e1c",
      "oklch": {
        "l": 0.1951,
        "c": 0.0379,
        "h": 333.7
      },
      "oklchCss": "oklch(0.195 0.038 333.7)"
    },
    "foreground": {
      "hex": "#f2dcea",
      "oklch": {
        "l": 0.9164,
        "c": 0.0303,
        "h": 339.3
      },
      "oklchCss": "oklch(0.916 0.03 339.3)"
    },
    "cursor": {
      "hex": "#f0c44e",
      "oklch": {
        "l": 0.838,
        "c": 0.1418,
        "h": 88.2
      },
      "oklchCss": "oklch(0.838 0.142 88.2)"
    },
    "selection": {
      "hex": "#3e2138",
      "oklch": {
        "l": 0.2956,
        "c": 0.0572,
        "h": 335
      },
      "oklchCss": "oklch(0.296 0.057 335)"
    },
    "black": {
      "hex": "#2f1629",
      "oklch": {
        "l": 0.2439,
        "c": 0.0506,
        "h": 336.6
      },
      "oklchCss": "oklch(0.244 0.051 336.6)"
    },
    "red": {
      "hex": "#ee5c82",
      "oklch": {
        "l": 0.6732,
        "c": 0.1818,
        "h": 7.4
      },
      "oklchCss": "oklch(0.673 0.182 7.4)"
    },
    "green": {
      "hex": "#9ad08a",
      "oklch": {
        "l": 0.8027,
        "c": 0.1109,
        "h": 138.7
      },
      "oklchCss": "oklch(0.803 0.111 138.7)"
    },
    "yellow": {
      "hex": "#f0c44e",
      "oklch": {
        "l": 0.838,
        "c": 0.1418,
        "h": 88.2
      },
      "oklchCss": "oklch(0.838 0.142 88.2)"
    },
    "blue": {
      "hex": "#b392e8",
      "oklch": {
        "l": 0.7229,
        "c": 0.1262,
        "h": 301
      },
      "oklchCss": "oklch(0.723 0.126 301)"
    },
    "purple": {
      "hex": "#d087e0",
      "oklch": {
        "l": 0.7294,
        "c": 0.1466,
        "h": 320.2
      },
      "oklchCss": "oklch(0.729 0.147 320.2)"
    },
    "cyan": {
      "hex": "#6fd0c8",
      "oklch": {
        "l": 0.7962,
        "c": 0.0928,
        "h": 188.5
      },
      "oklchCss": "oklch(0.796 0.093 188.5)"
    },
    "white": {
      "hex": "#e2c8d8",
      "oklch": {
        "l": 0.8592,
        "c": 0.036,
        "h": 340.4
      },
      "oklchCss": "oklch(0.859 0.036 340.4)"
    },
    "brightBlack": {
      "hex": "#836075",
      "oklch": {
        "l": 0.532,
        "c": 0.0544,
        "h": 342.4
      },
      "oklchCss": "oklch(0.532 0.054 342.4)"
    },
    "brightRed": {
      "hex": "#ee5c82",
      "oklch": {
        "l": 0.6732,
        "c": 0.1818,
        "h": 7.4
      },
      "oklchCss": "oklch(0.673 0.182 7.4)"
    },
    "brightGreen": {
      "hex": "#9ad08a",
      "oklch": {
        "l": 0.8027,
        "c": 0.1109,
        "h": 138.7
      },
      "oklchCss": "oklch(0.803 0.111 138.7)"
    },
    "brightYellow": {
      "hex": "#e8964f",
      "oklch": {
        "l": 0.743,
        "c": 0.1313,
        "h": 59.5
      },
      "oklchCss": "oklch(0.743 0.131 59.5)"
    },
    "brightBlue": {
      "hex": "#b392e8",
      "oklch": {
        "l": 0.7229,
        "c": 0.1262,
        "h": 301
      },
      "oklchCss": "oklch(0.723 0.126 301)"
    },
    "brightPurple": {
      "hex": "#d087e0",
      "oklch": {
        "l": 0.7294,
        "c": 0.1466,
        "h": 320.2
      },
      "oklchCss": "oklch(0.729 0.147 320.2)"
    },
    "brightCyan": {
      "hex": "#6fd0c8",
      "oklch": {
        "l": 0.7962,
        "c": 0.0928,
        "h": 188.5
      },
      "oklchCss": "oklch(0.796 0.093 188.5)"
    },
    "brightWhite": {
      "hex": "#f2dcea",
      "oklch": {
        "l": 0.9164,
        "c": 0.0303,
        "h": 339.3
      },
      "oklchCss": "oklch(0.916 0.03 339.3)"
    }
  },
  "contrast": {
    "fgOnBg": 14.23817682186259,
    "minAnsi": 5.702561339887455,
    "minAnsiSlot": "red",
    "cursorOnBg": 11.171153420175218,
    "selectionContrast": 10.950400005775837,
    "brightnessOrdered": false,
    "brightnessViolations": [
      "brightRed",
      "brightGreen",
      "brightYellow",
      "brightBlue",
      "brightPurple",
      "brightCyan"
    ]
  },
  "apca": {
    "fgOnBg": -88.32063704043944,
    "minAnsi": -42.12924674141585,
    "minAnsiSlot": "red"
  },
  "cvd": {
    "deuteranopia": 1.5784084616978444,
    "protanopia": 1.9316302285825875,
    "tritanopia": 9.791008497056714
  },
  "accent": {
    "source": "cursor",
    "hex": "#f0c44e",
    "oklch": {
      "l": 0.838,
      "c": 0.1418,
      "h": 88.2
    },
    "oklchCss": "oklch(0.838 0.142 88.2)"
  },
  "dataviz": {
    "categorical": [
      {
        "hex": "#f0c44e",
        "oklch": {
          "l": 0.838,
          "c": 0.1418,
          "h": 88.2
        },
        "oklchCss": "oklch(0.838 0.142 88.2)"
      },
      {
        "hex": "#d087e0",
        "oklch": {
          "l": 0.7294,
          "c": 0.1466,
          "h": 320.2
        },
        "oklchCss": "oklch(0.729 0.147 320.2)"
      },
      {
        "hex": "#6fd0c8",
        "oklch": {
          "l": 0.7962,
          "c": 0.0928,
          "h": 188.5
        },
        "oklchCss": "oklch(0.796 0.093 188.5)"
      },
      {
        "hex": "#9ad08a",
        "oklch": {
          "l": 0.8027,
          "c": 0.1109,
          "h": 138.7
        },
        "oklchCss": "oklch(0.803 0.111 138.7)"
      },
      {
        "hex": "#ee5c82",
        "oklch": {
          "l": 0.6732,
          "c": 0.1818,
          "h": 7.4
        },
        "oklchCss": "oklch(0.673 0.182 7.4)"
      },
      {
        "hex": "#e8964f",
        "oklch": {
          "l": 0.743,
          "c": 0.1313,
          "h": 59.5
        },
        "oklchCss": "oklch(0.743 0.131 59.5)"
      }
    ],
    "sequential": [
      {
        "hex": "#151515",
        "oklch": {
          "l": 0.1951,
          "c": 0,
          "h": 88.2
        },
        "oklchCss": "oklch(0.195 0 88.2)"
      },
      {
        "hex": "#332e21",
        "oklch": {
          "l": 0.3023,
          "c": 0.0236,
          "h": 88.2
        },
        "oklchCss": "oklch(0.302 0.024 88.2)"
      },
      {
        "hex": "#55492b",
        "oklch": {
          "l": 0.4094,
          "c": 0.0473,
          "h": 88.2
        },
        "oklchCss": "oklch(0.409 0.047 88.2)"
      },
      {
        "hex": "#796635",
        "oklch": {
          "l": 0.5166,
          "c": 0.0709,
          "h": 88.2
        },
        "oklchCss": "oklch(0.517 0.071 88.2)"
      },
      {
        "hex": "#9f843e",
        "oklch": {
          "l": 0.6237,
          "c": 0.0945,
          "h": 88.2
        },
        "oklchCss": "oklch(0.624 0.095 88.2)"
      },
      {
        "hex": "#c7a346",
        "oklch": {
          "l": 0.7309,
          "c": 0.1182,
          "h": 88.2
        },
        "oklchCss": "oklch(0.731 0.118 88.2)"
      },
      {
        "hex": "#f0c44e",
        "oklch": {
          "l": 0.838,
          "c": 0.1418,
          "h": 88.2
        },
        "oklchCss": "oklch(0.838 0.142 88.2)"
      }
    ],
    "diverging": [
      {
        "hex": "#f0c44e",
        "oklch": {
          "l": 0.838,
          "c": 0.1418,
          "h": 88.2
        },
        "oklchCss": "oklch(0.838 0.142 88.2)"
      },
      {
        "hex": "#dec179",
        "oklch": {
          "l": 0.8199,
          "c": 0.097,
          "h": 88.2
        },
        "oklchCss": "oklch(0.82 0.097 88.2)"
      },
      {
        "hex": "#ccbd98",
        "oklch": {
          "l": 0.8018,
          "c": 0.0523,
          "h": 88.2
        },
        "oklchCss": "oklch(0.802 0.052 88.2)"
      },
      {
        "hex": "#bab8b3",
        "oklch": {
          "l": 0.7837,
          "c": 0.0075,
          "h": 88.2
        },
        "oklchCss": "oklch(0.784 0.008 88.2)"
      },
      {
        "hex": "#c3a8c8",
        "oklch": {
          "l": 0.7656,
          "c": 0.0539,
          "h": 320.2
        },
        "oklchCss": "oklch(0.766 0.054 320.2)"
      },
      {
        "hex": "#ca98d5",
        "oklch": {
          "l": 0.7475,
          "c": 0.1002,
          "h": 320.2
        },
        "oklchCss": "oklch(0.748 0.1 320.2)"
      },
      {
        "hex": "#d087e0",
        "oklch": {
          "l": 0.7294,
          "c": 0.1466,
          "h": 320.2
        },
        "oklchCss": "oklch(0.729 0.147 320.2)"
      }
    ]
  }
}
