{
  "name": "Tailwind Slate Dark",
  "background": "#020617",
  "foreground": "#f8fafc",
  "cursorColor": "#3b82f6",
  "selectionBackground": "#1e293b",
  "black": "#020617",
  "red": "#ef4444",
  "green": "#22c55e",
  "yellow": "#f59e0b",
  "blue": "#3b82f6",
  "purple": "#a855f7",
  "cyan": "#06b6d4",
  "white": "#cbd5e1",
  "brightBlack": "#475569",
  "brightRed": "#f87171",
  "brightGreen": "#4ade80",
  "brightYellow": "#fbbf24",
  "brightBlue": "#60a5fa",
  "brightPurple": "#c084fc",
  "brightCyan": "#22d3ee",
  "brightWhite": "#f8fafc"
}
